py_rtoon-0.1.0.dist-info/METADATA
py_rtoon-0.1.0.dist-info/WHEEL
py_rtoon-0.1.0.dist-info/licenses/LICENSE
py_rtoon/__init__.py
py_rtoon/_core.abi3.so
py_rtoon/_core.pyi
py_rtoon/py.typed
py_rtoon-0.1.0.dist-info/RECORD
