Metadata-Version: 2.4
Name: py-rtoon
Version: 0.1.0
Classifier: Development Status :: 4 - Beta
Classifier: Intended Audience :: Developers
Classifier: License :: OSI Approved :: MIT License
Classifier: Programming Language :: Python :: 3
Classifier: Programming Language :: Python :: 3.9
Classifier: Programming Language :: Python :: 3.10
Classifier: Programming Language :: Python :: 3.11
Classifier: Programming Language :: Python :: 3.12
Classifier: Programming Language :: Python :: 3.13
Classifier: Programming Language :: Rust
Classifier: Topic :: Software Development :: Libraries :: Python Modules
Classifier: Topic :: Text Processing
Classifier: Typing :: Typed
License-File: LICENSE
Summary: Python bindings for rtoon - Token-Oriented Object Notation for efficient LLM data serialization
Keywords: toon,serialization,llm,token-efficient,rust,pyo3,data-format
Author-email: Prem Chotepanit <prem.ch@ku.th>
License: MIT
Requires-Python: >=3.9
Project-URL: Homepage, https://github.com/premchotipanit/py-rtoon
Project-URL: Repository, https://github.com/premchotipanit/py-rtoon
Project-URL: Documentation, https://github.com/premchotipanit/py-rtoon#readme
Project-URL: Issues, https://github.com/premchotipanit/py-rtoon/issues
Project-URL: Changelog, https://github.com/premchotipanit/py-rtoon/releases
